__init__.py
pafdc_pycts/__init__.py
pafdc_pycts/calibration/__init__.py
pafdc_pycts/calibration/calibration.py
pafdc_pycts/connect/__init__.py
pafdc_pycts/connect/connect.py
pafdc_pycts/file/__init__.py
pafdc_pycts/file/keysight/__init__.py
pafdc_pycts/file/keysight/fileheader.py
pafdc_pycts/file/keysight/waveformheader.py
pafdc_pycts/manifold/__init__.py
pafdc_pycts/manifold/cell.py
pafdc_pycts/manifold/manifold.py
pafdc_pycts/manifold/manifoldutils.py
pafdc_pycts/mathutils/__init__.py
pafdc_pycts-0.3.4.dist-info/METADATA
pafdc_pycts-0.3.4.dist-info/WHEEL
pafdc_pycts-0.3.4.dist-info/top_level.txt
pafdc_pycts-0.3.4.dist-info/RECORD
