Metadata-Version: 2.1
Name: pafdc-pycts
Version: 0.3.4
Summary: Textile capacitive touch sensor tools and utilities.
Home-page: https://github.com/pafdc/pycts
Author: rjvallett
Author-email: rjvallett@drexel.edu
License: None
Requires-Dist: numpy
Requires-Dist: pyserial
